hobart_svg/__init__.py
hobart_svg/cli.py
hobart_svg/core.py
hobart_svg/geometry.py
hobart_svg/mesh.py
hobart_svg/package_version.py
hobart_svg/svg.py
hobart_svg/test_core.py
hobart_svg-0.4.1.dist-info/LICENSE
hobart_svg-0.4.1.dist-info/METADATA
hobart_svg-0.4.1.dist-info/WHEEL
hobart_svg-0.4.1.dist-info/top_level.txt
hobart_svg-0.4.1.dist-info/RECORD
