Metadata-Version: 2.1
Name: hobart-svg
Version: 0.4.1
Summary: Render polygons, polylines, and mesh cross sections to SVG
Home-page: https://github.com/lace/hobart-svg
Author: Metabolize
Author-email: github@paulmelnikow.com
License: UNKNOWN
Platform: UNKNOWN
Classifier: Development Status :: 2 - Pre-Alpha
Classifier: Intended Audience :: Other Audience
Classifier: Intended Audience :: Science/Research
Classifier: License :: OSI Approved :: BSD License
Classifier: Operating System :: OS Independent
Classifier: Programming Language :: Python :: 3
Classifier: Topic :: Artistic Software
Classifier: Topic :: Multimedia :: Graphics :: 3D Modeling
Classifier: Topic :: Scientific/Engineering :: Visualization
Requires-Python: >=3.6, <3.9
Requires-Dist: hobart (==1.0.0b1)
Requires-Dist: numpy
Requires-Dist: lacecore[obj] (==0.5.0)
Requires-Dist: polliwog (==1.0.0b10)
Requires-Dist: click (<8.0,>=7.0)
Requires-Dist: vg (>=1.5)
Requires-Dist: svgwrite (<2.0,>=1.3.1)
Requires-Dist: tri-again (<0.2,>=0.1.1)
